{"homeAlias":"/","nodes":{"/garden-improvements/":{"id":0,"title":"Garden Improvements","url":"/garden-improvements/","group":"none","home":false,"outBound":[],"neighbors":[],"backLinks":[],"noteIcon":"","hide":false,"size":0},"/media-i-have-consumed/podcasts/1-second-everyday-indie-hackers-podcast/":{"id":1,"title":"1 Second Everyday - Indie Hackers Podcast","url":"/media-i-have-consumed/podcasts/1-second-everyday-indie-hackers-podcast/","group":"Podcasts","home":false,"outBound":[],"neighbors":[],"backLinks":[],"noteIcon":"","hide":false,"size":0},"/media-i-ve-consumed/podcasts/1-second-everyday-indie-hackers-podcast/":{"id":2,"title":"1 Second Everyday - Indie Hackers Podcast","url":"/media-i-ve-consumed/podcasts/1-second-everyday-indie-hackers-podcast/","group":"Podcasts","home":false,"outBound":[],"neighbors":[],"backLinks":[],"noteIcon":"","hide":false,"size":0},"/my-first-page/":{"id":3,"title":"My first page","url":"/my-first-page/","group":"none","home":false,"outBound":[],"neighbors":["/"],"backLinks":["/"],"noteIcon":"","hide":false,"size":1},"/my-second-page/":{"id":4,"title":"My second page","url":"/my-second-page/","group":"none","home":false,"outBound":[],"neighbors":["/"],"backLinks":["/"],"noteIcon":"","hide":false,"size":1},"/projects/really-old-projects/brianiscool-tk/":{"id":5,"title":"brianiscool.tk","url":"/projects/really-old-projects/brianiscool-tk/","group":"Really Old Projects","home":false,"outBound":[],"neighbors":[],"backLinks":[],"noteIcon":"","hide":false,"size":0},"/":{"id":6,"title":"This is the beginning","url":"/","group":"none","home":true,"outBound":["/my-first-page/","/my-second-page/"],"neighbors":["/my-first-page/","/my-second-page/"],"backLinks":[],"noteIcon":"","hide":false,"size":2}},"links":[{"source":6,"target":3},{"source":6,"target":4}]}